{
    "Amazon": {
        "email": "angela@gmail.com",
        "password": ")5R1ewanZwR8on2%"
    },
    "Facebook": {
        "email": "angela@gmail.com",
        "password": "1DsZYEG)4!as!G"
    },
    "HAHA": {
        "email": "angela@gmail.com",
        "password": "A%)QvrbYNC9)g*R06bYt2G+(tOh5Y1Y*gZ2mw2e#hF&8KtS7$(qD3S5Cdrc&SqG%+N5#G)P7TQzB1pCX+Iv30lCMS+uk!#V*%yWxnz00WJQHltL4bz2Ud+%FA#Mm)i3T0J78)YLGa1RQ&!oQsc+2y4xzcJ25Je*npHA&&9gz+mpn+YF66gQ$(%VSz38#H8SVGJEW4xx5P3N$rk#cUd(8%(O#6sCKSO(3HIyyA8!p%Fqh"
    }
}